release_exporter/__init__.py
release_exporter/base.py
release_exporter/cli.py
release_exporter/exceptions.py
release_exporter/formatter.py
release_exporter/request.py
release_exporter/utils.py
release_exporter/version.py
release_exporter-1.1.3.dist-info/LICENSE
release_exporter-1.1.3.dist-info/METADATA
release_exporter-1.1.3.dist-info/WHEEL
release_exporter-1.1.3.dist-info/entry_points.txt
release_exporter-1.1.3.dist-info/RECORD
